skid_buffer/skid_buffer.v
module skid_buffer #(
    parameter WIDTH = 8
) (
    input clk,
    input rst_n,

    input in_valid,
    input [WIDTH-1:0] in_data,
    output reg in_ready,

    output reg out_valid,
    output reg [WIDTH-1:0] out_data,
    input out_ready
);

localparam HOLD0=0, HOLD1=1, HOLD2=2;
reg [1:0] state, next_state;

reg skid_valid;
wire in = in_valid && in_ready;
wire out = out_valid && out_ready;
reg [WIDTH-1:0] skid_data;

always @(*) begin
    out_valid = (state != HOLD0);
    in_ready = (state != HOLD2);
    case (state)
        HOLD0: begin
            if (in) begin
                next_state = HOLD1;
            end else begin
                next_state = HOLD0;
            end
        end
        HOLD1: begin
            if (!in && !out) begin
                next_state = HOLD1;
            end else if (!in && out) begin
                next_state = HOLD0;
            end else if (in && !out) begin
                next_state = HOLD2;
            end else begin
                next_state = HOLD1;
            end
        end
        HOLD2: begin
            if (out) begin
                next_state = HOLD1;
            end else begin
                next_state = HOLD2;
            end
        end
        default: next_state = HOLD0;
    endcase
end

always @(posedge clk) begin
    if (!rst_n) begin
        state <= HOLD0;
        out_data <= 0;
        skid_data <= 0;
    end else begin
        state <= next_state;

        if ((state == HOLD2) && out) begin
            out_data <= skid_data;
        end else if (((state == HOLD0) && in) || ((state == HOLD1) && out)) begin
            out_data <= in_data;
        end

        if ((state == HOLD1) && in && !out) begin
            skid_data <= in_data;
        end
    end
end

endmodule

skid_buffer/skid_buffer_tb.v
`timescale 1ns/1ps
//======================================================================
// skid_buffer_tb.v  --  self-checking testbench for skid_buffer
//
//   iverilog -o sim skid_buffer.v skid_buffer_tb.v && vvp sim
//   gtkwave skid_buffer_tb.vcd     # optional waveforms
//
// What it checks
//   * every accepted input beat leaves the buffer exactly once, in order
//   * nothing is dropped or duplicated under arbitrary back-pressure
//   * out_valid / out_data hold steady while a beat is stalled
//     (valid asserted, ready low)  -- the handshake stability rule
//   * in_ready deasserts when the buffer is full (2 beats held)
//   * full throughput: 64 beats in ~64 cycles when neither side bubbles
//   * no X on the handshake / payload during normal operation
//======================================================================
module skid_buffer_tb;

  localparam WIDTH = 8;

  // ---- DUT I/O ----
  reg              clk = 1'b0;
  reg              rst_n;
  reg              in_valid;
  reg  [WIDTH-1:0] in_data;
  wire             in_ready;
  wire             out_valid;
  wire [WIDTH-1:0] out_data;
  reg              out_ready;

  skid_buffer #(.WIDTH(WIDTH)) dut (
    .clk(clk), .rst_n(rst_n),
    .in_valid(in_valid), .in_data(in_data), .in_ready(in_ready),
    .out_valid(out_valid), .out_data(out_data), .out_ready(out_ready)
  );

  always #5 clk = ~clk;                  // 100 MHz

  // ---- scoreboard: expected-payload FIFO (buffer holds <=2, 256 is plenty) ----
  reg  [WIDTH-1:0] sb [0:255];
  reg  [7:0]       wrp, rdp;
  integer          n_sent, n_recv, n_err;

  // ---- stimulus knobs ----
  integer          in_bubble_pct, out_bubble_pct, target;
  reg  [WIDTH-1:0] sym;

  integer          c, guard;

  // 0..99
  function [6:0] pct;
    input integer unused;
    reg [31:0] r;
    begin
      r   = $random;
      pct = r % 100;
    end
  endfunction

  //------------------------------------------------------------------
  // producer: drives the input stream, obeys the stall obligation
  // (once in_valid is asserted, in_data/in_valid are held until accepted)
  //------------------------------------------------------------------
  task producer_step;
    begin
      if (in_valid && in_ready) begin         // beat accepted on the last posedge
        sym      = sym + 8'd1;
        in_valid = 1'b0;
      end
      if (!in_valid) begin                     // free to launch a fresh beat
        if (n_sent < target && pct(0) >= in_bubble_pct) begin
          in_valid = 1'b1;
          in_data  = sym;
        end
      end
      // otherwise: hold in_valid/in_data stable -> obligation honored
    end
  endtask

  //------------------------------------------------------------------
  // consumer: randomly (de)asserts out_ready
  //------------------------------------------------------------------
  task consumer_step;
    begin
      out_ready = (pct(0) >= out_bubble_pct);
    end
  endtask

  //------------------------------------------------------------------
  // monitor / checker  (samples pre-edge values at every posedge)
  //------------------------------------------------------------------
  reg             p_valid, p_ready;
  reg [WIDTH-1:0] p_data;

  always @(posedge clk) begin
    if (rst_n) begin
      // input transfer -> remember what we expect to see come out
      if (in_valid && in_ready) begin
        sb[wrp] = in_data;
        wrp     = wrp + 8'd1;
        n_sent  = n_sent + 1;
      end

      // output transfer -> check payload + ordering
      if (out_valid && out_ready) begin
        if (n_recv >= n_sent) begin
          $display("[%0t] ERROR: output beat but scoreboard empty (spurious/duplicate)",
                   $time);
          n_err = n_err + 1;
        end else if (out_data !== sb[rdp]) begin
          $display("[%0t] ERROR: payload mismatch beat %0d: got %02x exp %02x",
                   $time, n_recv, out_data, sb[rdp]);
          n_err = n_err + 1;
        end
        rdp    = rdp + 8'd1;
        n_recv = n_recv + 1;
      end

      // handshake stability: a beat offered but not taken must not change
      if (p_valid && !p_ready) begin
        if (out_valid !== 1'b1) begin
          $display("[%0t] ERROR: out_valid dropped while beat un-accepted", $time);
          n_err = n_err + 1;
        end
        if (out_data !== p_data) begin
          $display("[%0t] ERROR: out_data changed while beat un-accepted", $time);
          n_err = n_err + 1;
        end
      end

      // X screen
      if (out_valid === 1'bx || in_ready === 1'bx) begin
        $display("[%0t] ERROR: X on handshake (out_valid=%b in_ready=%b)",
                 $time, out_valid, in_ready);
        n_err = n_err + 1;
      end
      if (out_valid === 1'b1 && (^out_data) === 1'bx) begin
        $display("[%0t] ERROR: X on out_data while out_valid", $time);
        n_err = n_err + 1;
      end
    end
    p_valid <= out_valid;
    p_ready <= out_ready;
    p_data  <= out_data;
  end

  //------------------------------------------------------------------
  // helpers
  //------------------------------------------------------------------
  task do_reset;
    begin
      rst_n = 1'b0; in_valid = 1'b0; in_data = 0; out_ready = 1'b0;
      sym = 0; wrp = 0; rdp = 0; n_sent = 0; n_recv = 0;
      p_valid = 0; p_ready = 0; p_data = 0;
      repeat (3) @(negedge clk);
      rst_n = 1'b1;
      @(negedge clk);
    end
  endtask

  task step;                            // one cycle of stimulus
    begin
      @(negedge clk);
      producer_step;
      consumer_step;
    end
  endtask

  task run_random(input integer ib, input integer ob, input integer nb);
    integer g;
    begin
      do_reset;
      in_bubble_pct = ib; out_bubble_pct = ob; target = nb;
      g = 0;
      while (n_recv < target && g < nb*200 + 2000) begin
        step; g = g + 1;
      end
      // guaranteed flush: stop feeding, open the output
      in_bubble_pct = 100; out_bubble_pct = 0;
      repeat (32) step;
      if (n_recv === target)
        $display("Random(in=%0d%% out=%0d%%): ok   %0d beats in %0d cycles",
                 ib, ob, target, g);
      else begin
        $display("Random(in=%0d%% out=%0d%%): FAIL recv=%0d target=%0d",
                 ib, ob, n_recv, target);
        n_err = n_err + 1;
      end
    end
  endtask

  //------------------------------------------------------------------
  // test program
  //------------------------------------------------------------------
  initial begin
    $dumpfile("skid_buffer_tb.vcd");
    $dumpvars(0, skid_buffer_tb);
    n_err = 0;

    // ---- Test 1: full throughput, no bubbles either side ----
    do_reset;
    in_bubble_pct = 0; out_bubble_pct = 0; target = 64;
    c = 0;
    while (n_recv < target && c < 300) begin
      step; c = c + 1;
    end
    if (n_recv === target && c <= target + 8)
      $display("Test1 THROUGHPUT   : ok   %0d beats in %0d cycles", target, c);
    else begin
      $display("Test1 THROUGHPUT   : FAIL recv=%0d target=%0d cycles=%0d (expected ~%0d)",
               n_recv, target, c, target);
      n_err = n_err + 1;
    end

    // ---- Test 2: fill until full, verify in_ready drops, then drain ----
    do_reset;
    in_bubble_pct = 0; out_bubble_pct = 100; target = 16;
    repeat (12) step;
    if (in_ready !== 1'b0) begin
      $display("Test2 FULL         : FAIL in_ready=%b (buffer should be full)", in_ready);
      n_err = n_err + 1;
    end
    if (out_valid !== 1'b1) begin
      $display("Test2 FULL         : FAIL out_valid=%b (should be holding a beat)", out_valid);
      n_err = n_err + 1;
    end
    if (in_ready === 1'b0 && out_valid === 1'b1)
      $display("Test2 FULL         : ok   in_ready low, out_valid high, n_sent=%0d", n_sent);
    out_bubble_pct = 0;                 // release downstream
    guard = 0;
    while (n_recv < target && guard < 5000) begin
      step; guard = guard + 1;
    end
    if (n_recv === target)
      $display("Test2 STALL+DRAIN  : ok   %0d beats recovered", target);
    else begin
      $display("Test2 STALL+DRAIN  : FAIL recv=%0d target=%0d", n_recv, target);
      n_err = n_err + 1;
    end

    // ---- Test 3-6: randomized back-pressure ----
    run_random(30, 30, 400);
    run_random(80, 15, 400);   // starved input
    run_random(15, 80, 400);   // slow output
    run_random(50, 50, 800);

    $display("--------------------------------------------------");
    if (n_err == 0) $display("*** ALL TESTS PASSED ***");
    else            $display("*** %0d ERROR(S) ***", n_err);
    $display("--------------------------------------------------");
    $finish;
  end

  // global watchdog
  initial begin
    #5_000_000;
    $display("*** GLOBAL TIMEOUT -- something is hung ***");
    n_err = n_err + 1;
    $finish;
  end

endmodule

skid_buffer/skid_buffer_tb.vcd
$date
	Sat Sep  5 19:46:42 2026
$end
$version
	Icarus Verilog
$end
$timescale
	1ps
$end
$scope module skid_buffer_tb $end
$var wire 1 ! out_valid $end
$var wire 8 " out_data [7:0] $end
$var wire 1 # in_ready $end
$var parameter 32 $ WIDTH $end
$var reg 1 % clk $end
$var reg 8 & in_data [7:0] $end
$var reg 1 ' in_valid $end
$var reg 1 ( out_ready $end
$var reg 8 ) p_data [7:0] $end
$var reg 1 * p_ready $end
$var reg 1 + p_valid $end
$var reg 8 , rdp [7:0] $end
$var reg 1 - rst_n $end
$var reg 8 . sym [7:0] $end
$var reg 8 / wrp [7:0] $end
$var integer 32 0 c [31:0] $end
$var integer 32 1 guard [31:0] $end
$var integer 32 2 in_bubble_pct [31:0] $end
$var integer 32 3 n_err [31:0] $end
$var integer 32 4 n_recv [31:0] $end
$var integer 32 5 n_sent [31:0] $end
$var integer 32 6 out_bubble_pct [31:0] $end
$var integer 32 7 target [31:0] $end
$scope function pct $end
$var reg 32 8 r [31:0] $end
$var integer 32 9 unused [31:0] $end
$upscope $end
$scope module dut $end
$var wire 1 % clk $end
$var wire 1 : in $end
$var wire 8 ; in_data [7:0] $end
$var wire 1 ' in_valid $end
$var wire 1 < out $end
$var wire 1 ( out_ready $end
$var wire 1 - rst_n $end
$var parameter 32 = HOLD0 $end
$var parameter 32 > HOLD1 $end
$var parameter 32 ? HOLD2 $end
$var parameter 32 @ WIDTH $end
$var reg 1 # in_ready $end
$var reg 2 A next_state [1:0] $end
$var reg 8 B out_data [7:0] $end
$var reg 1 ! out_valid $end
$var reg 8 C skid_data [7:0] $end
$var reg 2 D state [1:0] $end
$upscope $end
$scope task consumer_step $end
$upscope $end
$scope task do_reset $end
$upscope $end
$scope task producer_step $end
$upscope $end
$scope task run_random $end
$var integer 32 E g [31:0] $end
$var integer 32 F ib [31:0] $end
$var integer 32 G nb [31:0] $end
$var integer 32 H ob [31:0] $end
$upscope $end
$scope task step $end
$upscope $end
$upscope $end
$enddefinitions $end
$comment Show the parameter values. $end
$dumpall
b1000 @
b10 ?
b1 >
b0 =
b1000 $
$end
#0
$dumpvars
bx H
bx G
bx F
bx E
bx D
bx C
bx B
b0 A
0<
b0 ;
0:
bx 9
bx 8
bx 7
bx 6
b0 5
b0 4
b0 3
bx 2
bx 1
bx 0
b0 /
b0 .
0-
b0 ,
0+
0*
b0 )
0(
0'
b0 &
0%
x#
bx "
x!
$end
#5000
1#
0!
b0 C
b0 "
b0 B
b0 D
bx )
x+
1%
#10000
0%
#15000
b0 )
0+
1%
#20000
0%
#25000
1%
#30000
1-
0%
#35000
1%
#40000
b0 0
b1000000 7
b0 6
b0 2
0%
#45000
1%
#50000
b1 A
1:
b1 0
1(
1'
b11000000100010010101111010000001 8
b0 9
0%
#55000
1<
b1 A
1!
1*
b1 D
b1 5
b1 /
1%
#60000
b10 0
b1 &
b1 ;
b10110001111100000101011001100011 8
1'
b1 .
0%
#65000
b1 "
b1 B
1+
b1 4
b1 ,
b10 5
b10 /
1%
#70000
b11 0
b10 &
b10 ;
b1000110110111111001100110001101 8
1'
b10 .
0%
#75000
b1 )
b10 "
b10 B
b10 4
b10 ,
b11 5
b11 /
1%
#80000
b100 0
b11 &
b11 ;
b10001001001101110101001000010010 8
1'
b11 .
0%
#85000
b11 "
b11 B
b10 )
b11 4
b11 ,
b100 5
b100 /
1%
#90000
b101 0
b100 &
b100 ;
b110110101111100110100001101 8
1'
b100 .
0%
#95000
b11 )
b100 "
b100 B
b100 4
b100 ,
b101 5
b101 /
1%
#100000
b110 0
b101 &
b101 ;
b11110100011011100110100111101 8
1'
b101 .
0%
#105000
b101 "
b101 B
b100 )
b101 4
b101 ,
b110 5
b110 /
1%
#110000
b111 0
b110 &
b110 ;
b1000110001011011111011110001100 8
1'
b110 .
0%
#115000
b101 )
b110 "
b110 B
b110 4
b110 ,
b111 5
b111 /
1%
#120000
b1000 0
b111 &
b111 ;
b11100011001101110010010011000110 8
1'
b111 .
0%
#125000
b111 "
b111 B
b110 )
b111 4
b111 ,
b1000 5
b1000 /
1%
#130000
b1001 0
b1000 &
b1000 ;
b11010101000100111101001010101010 8
1'
b1000 .
0%
#135000
b111 )
b1000 "
b1000 B
b1000 4
b1000 ,
b1001 5
b1001 /
1%
#140000
b1010 0
b1001 &
b1001 ;
b10111011110100100111001001110111 8
1'
b1001 .
0%
#145000
b1001 "
b1001 B
b1000 )
b1001 4
b1001 ,
b1010 5
b1010 /
1%
#150000
b1011 0
b1010 &
b1010 ;
b1000111111011001101101110001111 8
1'
b1010 .
0%
#155000
b1001 )
b1010 "
b1010 B
b1010 4
b1010 ,
b1011 5
b1011 /
1%
#160000
b1100 0
b1011 &
b1011 ;
b11100111011101101001011011001110 8
1'
b1011 .
0%
#165000
b1011 "
b1011 B
b1010 )
b1011 4
b1011 ,
b1100 5
b1100 /
1%
#170000
b1101 0
b1100 &
b1100 ;
b11100010110010100100111011000101 8
1'
b1100 .
0%
#175000
b1011 )
b1100 "
b1100 B
b1100 4
b1100 ,
b1101 5
b1101 /
1%
#180000
b1110 0
b1101 &
b1101 ;
b11011110100011100010100010111101 8
1'
b1101 .
0%
#185000
b1101 "
b1101 B
b1100 )
b1101 4
b1101 ,
b1110 5
b1110 /
1%
#190000
b1111 0
b1110 &
b1110 ;
b10110010101001110010011001100101 8
1'
b1110 .
0%
#195000
b1101 )
b1110 "
b1110 B
b1110 4
b1110 ,
b1111 5
b1111 /
1%
#200000
b10000 0
b1111 &
b1111 ;
b101011100111000011100001010 8
1'
b1111 .
0%
#205000
b1111 "
b1111 B
b1110 )
b1111 4
b1111 ,
b10000 5
b10000 /
1%
#210000
b10001 0
b10000 &
b10000 ;
b10000011001000010000100100000 8
1'
b10000 .
0%
#215000
b1111 )
b10000 "
b10000 B
b10000 4
b10000 ,
b10001 5
b10001 /
1%
#220000
b10010 0
b10001 &
b10001 ;
b11001110110011001100110010011101 8
1'
b10001 .
0%
#225000
b10001 "
b10001 B
b10000 )
b10001 4
b10001 ,
b10010 5
b10010 /
1%
#230000
b10011 0
b10010 &
b10010 ;
b10001001100000111011100000010011 8
1'
b10010 .
0%
#235000
b10001 )
b10010 "
b10010 B
b10010 4
b10010 ,
b10011 5
b10011 /
1%
#240000
b10100 0
b10011 &
b10011 ;
b10101001101001111101011001010011 8
1'
b10011 .
0%
#245000
b10011 "
b10011 B
b10010 )
b10011 4
b10011 ,
b10100 5
b10100 /
1%
#250000
b10101 0
b10100 &
b10100 ;
b11101010101001100010101011010101 8
1'
b10100 .
0%
#255000
b10011 )
b10100 "
b10100 B
b10100 4
b10100 ,
b10101 5
b10101 /
1%
#260000
b10110 0
b10101 &
b10101 ;
b11010111010101100011111010101110 8
1'
b10101 .
0%
#265000
b10101 "
b10101 B
b10100 )
b10101 4
b10101 ,
b10110 5
b10110 /
1%
#270000
b10111 0
b10110 &
b10110 ;
b11100111110001010111001011001111 8
1'
b10110 .
0%
#275000
b10101 )
b10110 "
b10110 B
b10110 4
b10110 ,
b10111 5
b10111 /
1%
#280000
b11000 0
b10111 &
b10111 ;
b101000010010110010100001010 8
1'
b10111 .
0%
#285000
b10111 "
b10111 B
b10110 )
b10111 4
b10111 ,
b11000 5
b11000 /
1%
#290000
b11001 0
b11000 &
b11000 ;
b10011110001100010100110000111100 8
1'
b11000 .
0%
#295000
b10111 )
b11000 "
b11000 B
b11000 4
b11000 ,
b11001 5
b11001 /
1%
#300000
b11010 0
b11001 &
b11001 ;
b1000101001011100110000110001010 8
1'
b11001 .
0%
#305000
b11001 "
b11001 B
b11000 )
b11001 4
b11001 ,
b11010 5
b11010 /
1%
#310000
b11011 0
b11010 &
b11010 ;
b11101100010010110011010011011000 8
1'
b11010 .
0%
#315000
b11001 )
b11010 "
b11010 B
b11010 4
b11010 ,
b11011 5
b11011 /
1%
#320000
b11100 0
b11011 &
b11011 ;
b11000100100010100001001010001001 8
1'
b11011 .
0%
#325000
b11011 "
b11011 B
b11010 )
b11011 4
b11011 ,
b11100 5
b11100 /
1%
#330000
b11101 0
b11100 &
b11100 ;
b1011011000000100110010110110110 8
1'
b11100 .
0%
#335000
b11011 )
b11100 "
b11100 B
b11100 4
b11100 ,
b11101 5
b11101 /
1%
#340000
b11110 0
b11101 &
b11101 ;
b1010111000101010001001110101110 8
1'
b11101 .
0%
#345000
b11101 "
b11101 B
b11100 )
b11101 4
b11101 ,
b11110 5
b11110 /
1%
#350000
b11111 0
b11110 &
b11110 ;
b10101000011111101110100101010 8
1'
b11110 .
0%
#355000
b11101 )
b11110 "
b11110 B
b11110 4
b11110 ,
b11111 5
b11111 /
1%
#360000
b100000 0
b11111 &
b11111 ;
b10111000100101111011111001110001 8
1'
b11111 .
0%
#365000
b11111 "
b11111 B
b11110 )
b11111 4
b11111 ,
b100000 5
b100000 /
1%
#370000
b100001 0
b100000 &
b100000 ;
b100111111100100101010101001111 8
1'
b100000 .
0%
#375000
b11111 )
b100000 "
b100000 B
b100000 4
b100000 ,
b100001 5
b100001 /
1%
#380000
b100010 0
b100001 &
b100001 ;
b11101000001100011001100111010 8
1'
b100001 .
0%
#385000
b100001 "
b100001 B
b100000 )
b100001 4
b100001 ,
b100010 5
b100010 /
1%
#390000
b100011 0
b100010 &
b100010 ;
b1010101010100100101100010101 8
1'
b100010 .
0%
#395000
b100001 )
b100010 "
b100010 B
b100010 4
b100010 ,
b100011 5
b100011 /
1%
#400000
b100100 0
b100011 &
b100011 ;
b1101100100111000100101111011001 8
1'
b100011 .
0%
#405000
b100011 "
b100011 B
b100010 )
b100011 4
b100011 ,
b100100 5
b100100 /
1%
#410000
b100101 0
b100100 &
b100100 ;
b100110001101011111101101001100 8
1'
b100100 .
0%
#415000
b100011 )
b100100 "
b100100 B
b100100 4
b100100 ,
b100101 5
b100101 /
1%
#420000
b100110 0
b100101 &
b100101 ;
b1000111101110011010000110001111 8
1'
b100101 .
0%
#425000
b100101 "
b100101 B
b100100 )
b100101 4
b100101 ,
b100110 5
b100110 /
1%
#430000
b100111 0
b100110 &
b100110 ;
b11011011110011010110000010110111 8
1'
b100110 .
0%
#435000
b100101 )
b100110 "
b100110 B
b100110 4
b100110 ,
b100111 5
b100111 /
1%
#440000
b101000 0
b100111 &
b100111 ;
b10101110011111011001010001011100 8
1'
b100111 .
0%
#445000
b100111 "
b100111 B
b100110 )
b100111 4
b100111 ,
b101000 5
b101000 /
1%
#450000
b101001 0
b101000 &
b101000 ;
b1000100110111100011011110001001 8
1'
b101000 .
0%
#455000
b100111 )
b101000 "
b101000 B
b101000 4
b101000 ,
b101001 5
b101001 /
1%
#460000
b101010 0
b101001 &
b101001 ;
b11101000001000110011111011010000 8
1'
b101001 .
0%
#465000
b101001 "
b101001 B
b101000 )
b101001 4
b101001 ,
b101010 5
b101010 /
1%
#470000
b101011 0
b101010 &
b101010 ;
b10101000110001111111110001010001 8
1'
b101010 .
0%
#475000
b101001 )
b101010 "
b101010 B
b101010 4
b101010 ,
b101011 5
b101011 /
1%
#480000
b101100 0
b101011 &
b101011 ;
b110000111010111111100001100 8
1'
b101011 .
0%
#485000
b101011 "
b101011 B
b101010 )
b101011 4
b101011 ,
b101100 5
b101100 /
1%
#490000
b101101 0
b101100 &
b101100 ;
b1100100010101111110110111001000 8
1'
b101100 .
0%
#495000
b101011 )
b101100 "
b101100 B
b101100 4
b101100 ,
b101101 5
b101101 /
1%
#500000
b101110 0
b101101 &
b101101 ;
b11110111100101110110100111101 8
1'
b101101 .
0%
#505000
b101101 "
b101101 B
b101100 )
b101101 4
b101101 ,
b101110 5
b101110 /
1%
#510000
b101111 0
b101110 &
b101110 ;
b10111111000001010000000001111110 8
1'
b101110 .
0%
#515000
b101101 )
b101110 "
b101110 B
b101110 4
b101110 ,
b101111 5
b101111 /
1%
#520000
b110000 0
b101111 &
b101111 ;
b11100110110011110011100111001 8
1'
b101111 .
0%
#525000
b101111 "
b101111 B
b101110 )
b101111 4
b101111 ,
b110000 5
b110000 /
1%
#530000
b110001 0
b110000 &
b110000 ;
b11101001111010111111011011010011 8
1'
b110000 .
0%
#535000
b101111 )
b110000 "
b110000 B
b110000 4
b110000 ,
b110001 5
b110001 /
1%
#540000
b110010 0
b110001 &
b110001 ;
b10111100000101001000100001111000 8
1'
b110001 .
0%
#545000
b110001 "
b110001 B
b110000 )
b110001 4
b110001 ,
b110010 5
b110010 /
1%
#550000
b110011 0
b110010 &
b110010 ;
b100100100010110100101101001001 8
1'
b110010 .
0%
#555000
b110001 )
b110010 "
b110010 B
b110010 4
b110010 ,
b110011 5
b110011 /
1%
#560000
b110100 0
b110011 &
b110011 ;
b10101000011001010111100101010 8
1'
b110011 .
0%
#565000
b110011 "
b110011 B
b110010 )
b110011 4
b110011 ,
b110100 5
b110100 /
1%
#570000
b110101 0
b110100 &
b110100 ;
b11000011001111110011100010000110 8
1'
b110100 .
0%
#575000
b110011 )
b110100 "
b110100 B
b110100 4
b110100 ,
b110101 5
b110101 /
1%
#580000
b110110 0
b110101 &
b110101 ;
b11001110001011111111001010011100 8
1'
b110101 .
0%
#585000
b110101 "
b110101 B
b110100 )
b110101 4
b110101 ,
b110110 5
b110110 /
1%
#590000
b110111 0
b110110 &
b110110 ;
b10010011011111011011110000100110 8
1'
b110110 .
0%
#595000
b110101 )
b110110 "
b110110 B
b110110 4
b110110 ,
b110111 5
b110111 /
1%
#600000
b111000 0
b110111 &
b110111 ;
b11010001100010111011010010100011 8
1'
b110111 .
0%
#605000
b110111 "
b110111 B
b110110 )
b110111 4
b110111 ,
b111000 5
b111000 /
1%
#610000
b111001 0
b111000 &
b111000 ;
b11011001110100101001001010110011 8
1'
b111000 .
0%
#615000
b110111 )
b111000 "
b111000 B
b111000 4
b111000 ,
b111001 5
b111001 /
1%
#620000
b111010 0
b111001 &
b111001 ;
b100010001010010000110101000100 8
1'
b111001 .
0%
#625000
b111001 "
b111001 B
b111000 )
b111001 4
b111001 ,
b111010 5
b111010 /
1%
#630000
b111011 0
b111010 &
b111010 ;
b11100101100110110011011011001011 8
1'
b111010 .
0%
#635000
b111001 )
b111010 "
b111010 B
b111010 4
b111010 ,
b111011 5
b111011 /
1%
#640000
b111100 0
b111011 &
b111011 ;
b101101001010001101101101011010 8
1'
b111011 .
0%
#645000
b111011 "
b111011 B
b111010 )
b111011 4
b111011 ,
b111100 5
b111100 /
1%
#650000
b111101 0
b111100 &
b111100 ;
b11110110100000101110001011101101 8
1'
b111100 .
0%
#655000
b111011 )
b111100 "
b111100 B
b111100 4
b111100 ,
b111101 5
b111101 /
1%
#660000
b111110 0
b111101 &
b111101 ;
b10110010100111111011011001100101 8
1'
b111101 .
0%
#665000
b111101 "
b111101 B
b111100 )
b111101 4
b111101 ,
b111110 5
b111110 /
1%
#670000
b111111 0
b111110 &
b111110 ;
b11101111101111101001010011011111 8
1'
b111110 .
0%
#675000
b111101 )
b111110 "
b111110 B
b111110 4
b111110 ,
b111111 5
b111111 /
1%
#680000
b1000000 0
b111111 &
b111111 ;
b100010001100011111111101000100 8
1'
b111111 .
0%
#685000
b111111 "
b111111 B
b111110 )
b111111 4
b111111 ,
b1000000 5
b1000000 /
1%
#690000
b0 A
0:
b1000001 0
b11101000011101000000110011010000 8
0'
b1000000 .
0%
#695000
0<
0!
b111111 )
b0 D
b1000000 4
b1000000 ,
1%
#700000
b0 )
0*
0+
b0 4
b0 5
b0 ,
b0 /
b0 .
0(
b0 &
b0 ;
0-
b1000010 0
b10101000010010000101100101010 8
0%
#705000
b0 "
b0 B
b111111 )
1%
#710000
0%
#715000
b0 )
1%
#720000
0%
#725000
1%
#730000
1-
0%
#735000
1%
#740000
b10000 7
b1100100 6
0%
#745000
1%
#750000
b1 A
1:
1'
b111011011111100111100001110 8
0%
#755000
b10 A
1!
b1 D
b1 5
b1 /
1%
#760000
b1 &
b1 ;
b11001101010111101011110010011010 8
1'
b1 .
0%
#765000
0:
0#
b1 C
b1 "
b1 B
b10 D
1+
b10 5
b10 /
1%
#770000
b11111110110111110111001011111101 8
0%
#775000
b1 )
b1 3
1%
#780000
b11100001111100010000001011000011 8
0%
#785000
1%
#790000
b101011000011101110110101010110 8
0%
#795000
1%
#800000
b100111011110011110100101001110 8
0%
#805000
1%
#810000
b10110011110110010111011001100111 8
0%
#815000
1%
#820000
b10000101001100010011010000001010 8
0%
#825000
1%
#830000
b1011011011011111011100110110110 8
0%
#835000
1%
#840000
b10011100000011101000101000111000 8
0%
#845000
1%
#850000
b111100110100011000011101111001 8
0%
#855000
1%
#860000
b0 1
b0 6
b11011100001010111100010010111000 8
0%
#865000
1%
#870000
b1 A
1<
b1 1
1(
b1001010011101001011111110010100 8
0%
#875000
1:
b1 A
1#
1*
b1 D
b1 4
b1 ,
b10 3
1%
#880000
b10 1
b10 &
b10 ;
b10000010001111110010110000000100 8
1'
b10 .
0%
#885000
b10 "
b10 B
b10 4
b10 ,
b11 5
b11 /
1%
#890000
b11 1
b11 &
b11 ;
b1101101110010110110100111011011 8
1'
b11 .
0%
#895000
b10 )
b11 "
b11 B
b11 4
b11 ,
b100 5
b100 /
1%
#900000
b100 1
b100 &
b100 ;
b1101100101100001011011111011001 8
1'
b100 .
0%
#905000
b100 "
b100 B
b11 )
b100 4
b100 ,
b101 5
b101 /
1%
#910000
b101 1
b101 &
b101 ;
b10111011010001011110001001110110 8
1'
b101 .
0%
#915000
b100 )
b101 "
b101 B
b101 4
b101 ,
b110 5
b110 /
1%
#920000
b110 1
b110 &
b110 ;
b1011011000101110010110110110110 8
1'
b110 .
0%
#925000
b110 "
b110 B
b101 )
b110 4
b110 ,
b111 5
b111 /
1%
#930000
b111 1
b111 &
b111 ;
b10100011000001110001101001000110 8
1'
b111 .
0%
#935000
b110 )
b111 "
b111 B
b111 4
b111 ,
b1000 5
b1000 /
1%
#940000
b1000 1
b1000 &
b1000 ;
b1111011110100100110000111110111 8
1'
b1000 .
0%
#945000
b1000 "
b1000 B
b111 )
b1000 4
b1000 ,
b1001 5
b1001 /
1%
#950000
b1001 1
b1001 &
b1001 ;
b11011010011011101011101010110100 8
1'
b1001 .
0%
#955000
b1000 )
b1001 "
b1001 B
b1001 4
b1001 ,
b1010 5
b1010 /
1%
#960000
b1010 1
b1010 &
b1010 ;
b10100011111001101100100101000 8
1'
b1010 .
0%
#965000
b1010 "
b1010 B
b1001 )
b1010 4
b1010 ,
b1011 5
b1011 /
1%
#970000
b1011 1
b1011 &
b1011 ;
b11100011110001010011000011000111 8
1'
b1011 .
0%
#975000
b1010 )
b1011 "
b1011 B
b1011 4
b1011 ,
b1100 5
b1100 /
1%
#980000
b1100 1
b1100 &
b1100 ;
b10000100011101111110010000001000 8
1'
b1100 .
0%
#985000
b1100 "
b1100 B
b1011 )
b1100 4
b1100 ,
b1101 5
b1101 /
1%
#990000
b1101 1
b1101 &
b1101 ;
b11111110101001111010011011111101 8
1'
b1101 .
0%
#995000
b1100 )
b1101 "
b1101 B
b1101 4
b1101 ,
b1110 5
b1110 /
1%
#1000000
b1110 1
b1110 &
b1110 ;
b10001110001101111001000000011100 8
1'
b1110 .
0%
#1005000
b1110 "
b1110 B
b1101 )
b1110 4
b1110 ,
b1111 5
b1111 /
1%
#1010000
b1111 1
b1111 &
b1111 ;
b11101101001101000000100011011010 8
1'
b1111 .
0%
#1015000
b1110 )
b1111 "
b1111 B
b1111 4
b1111 ,
b10000 5
b10000 /
1%
#1020000
b0 A
0:
b10000 1
b10011110101101111100011000111101 8
0'
b10000 .
0%
#1025000
0<
0!
b0 D
b1111 )
b10000 4
b10000 ,
1%
#1030000
b0 )
0*
0+
b0 4
b0 5
b0 ,
b0 /
b0 .
0(
b0 &
b0 ;
0-
b110010000 G
b11110 H
b11110 F
b10001 1
b110011010011101010011101100110 8
0%
#1035000
b1111 )
b0 C
b0 "
b0 B
1%
#1040000
0%
#1045000
b0 )
1%
#1050000
0%
#1055000
1%
#1060000
1-
0%
#1065000
1%
#1070000
b0 E
b110010000 7
b11110 6
b11110 2
0%
#1075000
1%
#1080000
b1 A
1:
b1 E
1'
b10111001111101010000010001110011 8
0%
#1085000
b10 A
1!
b1 D
b1 5
b1 /
1%
#1090000
b0 A
1<
0:
b10 E
1(
b101111001110101011001101011110 8
0'
b1 .
0%
#1095000
0<
0!
1*
1+
b0 D
b1 4
b1 ,
1%
#1100000
b1 A
1:
b11 E
0(
b1 &
b1 ;
1'
b1101010100011100000010111010101 8
0%
#1105000
b10 A
1!
b1 "
b1 B
b1 D
0*
0+
b10 5
b10 /
1%
#1110000
b1 A
1<
b100 E
1(
b10 &
b10 ;
b11011100111100000000000010111001 8
1'
b10 .
0%
#1115000
b1 )
1*
1+
b10 "
b10 B
b10 4
b10 ,
b11 5
b11 /
1%
#1120000
b101 E
b11 &
b11 ;
b1001011001001110011011110010110 8
1'
b11 .
0%
#1125000
b11 "
b11 B
b10 )
b11 4
b11 ,
b100 5
b100 /
1%
#1130000
b0 A
0:
b110 E
b10011001001011001111100100110 8
0'
b100 .
0%
