async_fifo/async_fifo.sv
module async_fifo (
    input wr_clk,
    input rd_clk,
    input rst_n,
    input wr_en,
    input [7:0] wr_data,
    input rd_en,

    output [7:0] rd_data,
    output full,
    output empty
);

reg [7:0] data [0:15];
wire [4:0] rd_ptr_gray, wr_ptr_gray, rd_ptr_transferred, wr_ptr_transferred;
reg [4:0] rd_ptr, wr_ptr, rd_ptr_gray_asynced, rd_ptr_gray_synced, wr_ptr_gray_asynced, wr_ptr_gray_synced;

norm_to_gray read (.in(rd_ptr), .out(rd_ptr_gray));
norm_to_gray write (.in(wr_ptr), .out(wr_ptr_gray));
gray_to_norm read_transfer (.in(rd_ptr_gray_synced), .out(rd_ptr_transferred));
gray_to_norm write_transfer (.in(wr_ptr_gray_synced), .out(wr_ptr_transferred));

always @(posedge wr_clk, negedge rst_n) begin
    if (!rst_n) begin
        wr_ptr <= 0;
        rd_ptr_gray_asynced <= 0;
        rd_ptr_gray_synced <= 0;
    end else begin
        rd_ptr_gray_asynced <= rd_ptr_gray;
        rd_ptr_gray_synced <= rd_ptr_gray_asynced;
        if (wr_en && !full) begin
            wr_ptr <= wr_ptr + 1;
            data[wr_ptr[3:0]] <= wr_data;
        end
    end
end

always @(posedge rd_clk, negedge rst_n) begin
    if (!rst_n) begin
        rd_ptr <= 0;
        wr_ptr_gray_asynced <= 0;
        wr_ptr_gray_synced <= 0;
    end else begin
        wr_ptr_gray_asynced <= wr_ptr_gray;
        wr_ptr_gray_synced <= wr_ptr_gray_asynced;
        if (rd_en && !empty) begin
            rd_ptr <= rd_ptr + 1;
        end
    end
end

assign empty = (wr_ptr_transferred[4] == rd_ptr[4]) && (wr_ptr_transferred[3:0] == rd_ptr[3:0]);
assign full = (wr_ptr[4] != rd_ptr_transferred[4]) && (wr_ptr[3:0] == rd_ptr_transferred[3:0]);
assign rd_data = data[rd_ptr[3:0]];

endmodule

module norm_to_gray (
    input [4:0] in,
    output reg [4:0] out
);

always @(*) begin
    out = in ^ (in >> 1);
end

endmodule

module gray_to_norm (
    input [4:0] in,
    output reg [4:0] out
);

always @(*) begin
    out[4] = in[4];
    for (int i=3; i>=0; i--) begin
        out[i] = out[i+1] ^ in[i];
    end
end

endmodule

async_fifo/async_fifo_tb.sv
`timescale 1ns/1ps
//
// Testbench for async_fifo.sv
//
//  - two asynchronous clocks (write faster than read, then swapped in a 2nd pass)
//  - reference model (SystemVerilog queue) acts as a golden FIFO
//  - self-checking: data integrity, overflow (write accepted while "really" full),
//    underflow (read accepted while "really" empty)
//
// Run with Icarus:
//   iverilog -g2012 -o sim.out async_fifo.sv async_fifo_tb.sv && vvp sim.out
//
module async_fifo_tb;

  localparam int DEPTH = 16;   // must match the DUT memory depth

  // ---------------------------------------------------------------- DUT I/O
  logic        wr_clk = 0;
  logic        rd_clk = 0;
  logic        rst_n;
  logic        wr_en;
  logic [7:0]  wr_data;
  logic        rd_en;
  logic [7:0]  rd_data;
  logic        full;
  logic        empty;

  async_fifo dut (
    .wr_clk (wr_clk),
    .rd_clk (rd_clk),
    .rst_n  (rst_n),
    .wr_en  (wr_en),
    .wr_data(wr_data),
    .rd_en  (rd_en),
    .rd_data(rd_data),
    .full   (full),
    .empty  (empty)
  );

  // ---------------------------------------------------------------- clocks
  real wr_half = 5.0;    // 10 ns  write clock
  real rd_half = 7.0;    // 14 ns  read  clock
  always #(wr_half) wr_clk = ~wr_clk;
  always #(rd_half) rd_clk = ~rd_clk;

  // ---------------------------------------------------------------- scoreboard
  logic [7:0] model_q [$];
  int errors      = 0;
  int writes_done = 0;
  int reads_done  = 0;

  task automatic flag(input string msg);
    $display("  *** ERROR @%0t: %s", $time, msg);
    errors++;
  endtask

  // Write side: a write is "accepted" on the wr_clk edge when wr_en & !full.
  always @(posedge wr_clk) begin
    if (rst_n === 1'b1 && wr_en && !full) begin
      if (model_q.size() >= DEPTH)
        flag($sformatf("OVERFLOW - write accepted, model already holds %0d entries", model_q.size()));
      model_q.push_back(wr_data);
      writes_done++;
    end
  end

  // Read side: async_fifo drives rd_data combinationally from the current
  // rd_ptr and advances rd_ptr on this same posedge, so the consumed beat must
  // be sampled with the pre-edge values, i.e. right here on posedge rd_clk.
  always @(posedge rd_clk) begin
    logic [7:0] exp;
    if (rst_n === 1'b1 && rd_en && !empty) begin
      if (model_q.size() == 0) begin
        flag("UNDERFLOW - DUT reports !empty but golden model is empty");
      end else begin
        exp = model_q.pop_front();
        if (rd_data !== exp)
          flag($sformatf("DATA MISMATCH - got 0x%02h expected 0x%02h", rd_data, exp));
        reads_done++;
      end
    end
  end

  // ---------------------------------------------------------------- helpers
  task automatic do_reset;
    wr_en   = 0;
    rd_en   = 0;
    wr_data = 0;
    rst_n   = 0;
    repeat (4) @(posedge wr_clk);
    repeat (4) @(posedge rd_clk);
    @(negedge wr_clk) rst_n = 1;
    model_q.delete();
    repeat (2) @(posedge wr_clk);
  endtask

  // continuously drive writes for n wr_clk cycles with a given assert probability
  task automatic drive_writes(input int cycles, input int pct);
    for (int i = 0; i < cycles; i++) begin
      @(negedge wr_clk);
      if (($urandom_range(0,99)) < pct) begin
        wr_en   <= 1'b1;
        wr_data <= $urandom;
      end else begin
        wr_en <= 1'b0;
      end
    end
    @(negedge wr_clk) wr_en <= 1'b0;
  endtask

  task automatic drive_reads(input int cycles, input int pct);
    for (int i = 0; i < cycles; i++) begin
      @(negedge rd_clk);
      rd_en <= (($urandom_range(0,99)) < pct);
    end
    @(negedge rd_clk) rd_en <= 1'b0;
  endtask

  // ---------------------------------------------------------------- tests
  initial begin
    $dumpfile("async_fifo_tb.vcd");
    $dumpvars(0, async_fifo_tb);

    // -------- Test 0: reset behaviour
    $display("[Test 0] reset");
    do_reset();
    if (empty !== 1'b1) flag("after reset: empty should be 1");
    if (full  !== 1'b0) flag("after reset: full should be 0");

    // -------- Test 1: fill the FIFO with no reads, then drain it
    $display("[Test 1] fill then drain, check data order & no overflow");
    fork
      drive_writes(DEPTH + 8, 100);   // push harder than it can hold
    join
    repeat (10) @(posedge wr_clk);    // let full propagate
    if (!full)
      flag($sformatf("FIFO not full after %0d write attempts (accepted %0d)", DEPTH+8, writes_done));

    drive_reads(DEPTH + 20, 100);
    repeat (10) @(posedge rd_clk);
    if (!empty) flag("FIFO not empty after draining");
    if (model_q.size() != 0)
      flag($sformatf("golden model still holds %0d entries after drain", model_q.size()));

    // -------- Test 2: concurrent random read/write, write-heavy
    $display("[Test 2] random concurrent traffic (write-heavy)");
    do_reset();
    fork
      drive_writes(400, 75);
      drive_reads (400, 40);
    join
    // drain remainder
    drive_reads(600, 100);
    repeat (10) @(posedge rd_clk);
    if (model_q.size() != 0)
      flag($sformatf("Test 2: %0d entries left unread", model_q.size()));

    // -------- Test 3: random concurrent traffic, read-heavy
    $display("[Test 3] random concurrent traffic (read-heavy)");
    do_reset();
    fork
      drive_writes(400, 35);
      drive_reads (400, 90);
    join
    drive_reads(400, 100);
    repeat (10) @(posedge rd_clk);
    if (model_q.size() != 0)
      flag($sformatf("Test 3: %0d entries left unread", model_q.size()));

    // -------- Test 4: swap clock rates (read faster than write)
    $display("[Test 4] read clock faster than write clock");
    wr_half = 8.0;   // 16 ns
    rd_half = 3.0;   //  6 ns
    do_reset();
    fork
      drive_writes(300, 60);
      drive_reads (800, 70);
    join
    drive_reads(400, 100);
    repeat (10) @(posedge rd_clk);
    if (model_q.size() != 0)
      flag($sformatf("Test 4: %0d entries left unread", model_q.size()));

    // ---------------------------------------------------------------- summary
    $display("--------------------------------------------------");
    $display("writes accepted : %0d", writes_done);
    $display("reads  checked  : %0d", reads_done);
    if (errors == 0) $display("RESULT: PASS");
    else             $display("RESULT: FAIL (%0d errors)", errors);
    $display("--------------------------------------------------");
    $finish;
  end

  // global watchdog
  initial begin
    #500000;
    $display("*** ERROR: watchdog timeout");
    $finish;
  end

endmodule

async_fifo/async_fifo_tb.vcd
$date
	Sat Sep  5 15:50:06 2026
$end
$version
	Icarus Verilog
$end
$timescale
	1ps
$end
$scope module async_fifo_tb $end
$var wire 8 ! rd_data [7:0] $end
$var wire 1 " full $end
$var wire 1 # empty $end
$var parameter 32 $ DEPTH $end
$var reg 1 % rd_clk $end
$var reg 1 & rd_en $end
$var reg 1 ' rst_n $end
$var reg 1 ( wr_clk $end
$var reg 8 ) wr_data [7:0] $end
$var reg 1 * wr_en $end
$var integer 32 + errors [31:0] $end
$var real 1 , rd_half $end
$var integer 32 - reads_done [31:0] $end
$var real 1 . wr_half $end
$var integer 32 / writes_done [31:0] $end
$scope module dut $end
$var wire 1 # empty $end
$var wire 1 " full $end
$var wire 1 % rd_clk $end
$var wire 8 0 rd_data [7:0] $end
$var wire 1 & rd_en $end
$var wire 1 ' rst_n $end
$var wire 1 ( wr_clk $end
$var wire 8 1 wr_data [7:0] $end
$var wire 1 * wr_en $end
$var wire 5 2 wr_ptr_transferred [4:0] $end
$var wire 5 3 wr_ptr_gray [4:0] $end
$var wire 5 4 rd_ptr_transferred [4:0] $end
$var wire 5 5 rd_ptr_gray [4:0] $end
$var reg 5 6 rd_ptr [4:0] $end
$var reg 5 7 rd_ptr_gray_asynced [4:0] $end
$var reg 5 8 rd_ptr_gray_synced [4:0] $end
$var reg 5 9 wr_ptr [4:0] $end
$var reg 5 : wr_ptr_gray_asynced [4:0] $end
$var reg 5 ; wr_ptr_gray_synced [4:0] $end
$scope module read $end
$var wire 5 < in [4:0] $end
$var reg 5 = out [4:0] $end
$upscope $end
$scope module read_transfer $end
$var wire 5 > in [4:0] $end
$var reg 5 ? out [4:0] $end
$scope begin $ivl_for_loop0 $end
$var integer 32 @ i [31:0] $end
$upscope $end
$upscope $end
$scope module write $end
$var wire 5 A in [4:0] $end
$var reg 5 B out [4:0] $end
$upscope $end
$scope module write_transfer $end
$var wire 5 C in [4:0] $end
$var reg 5 D out [4:0] $end
$scope begin $ivl_for_loop0 $end
$var integer 32 E i [31:0] $end
$upscope $end
$upscope $end
$upscope $end
$scope begin $unm_blk_14 $end
$var reg 8 F exp [7:0] $end
$upscope $end
$scope task do_reset $end
$upscope $end
$scope task drive_reads $end
$scope begin $ivl_for_loop2 $end
$upscope $end
$upscope $end
$scope task drive_writes $end
$scope begin $ivl_for_loop1 $end
$upscope $end
$upscope $end
$scope task flag $end
$upscope $end
$upscope $end
$enddefinitions $end
$comment Show the parameter values. $end
$dumpall
b10000 $
$end
#0
$dumpvars
bx F
b11111111111111111111111111111111 E
b0 D
b0 C
b0 B
b0 A
b11111111111111111111111111111111 @
b0 ?
b0 >
b0 =
b0 <
b0 ;
b0 :
b0 9
b0 8
b0 7
b0 6
b0 5
b0 4
b0 3
b0 2
b0 1
bx 0
b0 /
r5 .
b0 -
r7 ,
b0 +
0*
b0 )
0(
0'
0&
0%
1#
0"
bx !
$end
#5000
1(
#7000
1%
#10000
0(
#14000
0%
#15000
1(
#20000
0(
#21000
1%
#25000
1(
#28000
0%
#30000
0(
#35000
1(
1%
#40000
0(
#42000
0%
#45000
1(
#49000
1%
#50000
0(
#55000
1(
#56000
0%
#60000
0(
#63000
1%
#65000
1(
#70000
0(
0%
#75000
1(
#77000
1%
#80000
0(
#84000
0%
#85000
1(
#90000
0(
#91000
1%
#95000
1(
#98000
0%
#100000
1'
0(
#105000
1(
1%
#110000
0(
#112000
0%
#115000
1(
#119000
1%
#120000
b10000001 )
b10000001 1
1*
0(
#125000
b1 3
b1 B
b10000001 !
b10000001 0
b1 9
b1 A
b1 /
1(
#126000
0%
#130000
b1100011 )
b1100011 1
0(
#133000
b1 :
1%
#135000
b11 3
b11 B
b10 9
b10 A
b10 /
1(
#140000
b10001101 )
b10001101 1
0(
0%
#145000
b10 3
b10 B
b11 9
b11 A
b11 /
1(
#147000
0#
b1 2
b1 D
b11111111111111111111111111111111 E
b1 ;
b1 C
b10 :
1%
#150000
b10010 )
b10010 1
0(
#154000
0%
#155000
b110 3
b110 B
b100 9
b100 A
b100 /
1(
#160000
b1101 )
b1101 1
0(
#161000
b11 2
b11 D
b11111111111111111111111111111111 E
b10 ;
b10 C
b110 :
1%
#165000
b111 3
b111 B
b101 9
b101 A
b101 /
1(
#168000
0%
#170000
b111101 )
b111101 1
0(
#175000
b101 3
b101 B
b100 2
b100 D
b11111111111111111111111111111111 E
b110 9
b110 A
b110 ;
b110 C
b111 :
b110 /
1(
1%
#180000
b10001100 )
b10001100 1
0(
#182000
0%
#185000
b100 3
b100 B
b111 9
b111 A
b111 /
1(
#189000
b101 2
b101 D
b11111111111111111111111111111111 E
b111 ;
b111 C
b100 :
1%
#190000
b11000110 )
b11000110 1
0(
#195000
b1100 3
b1100 B
b1000 9
b1000 A
b1000 /
1(
#196000
0%
#200000
b10101010 )
b10101010 1
0(
#203000
b111 2
b111 D
b11111111111111111111111111111111 E
b100 ;
b100 C
b1100 :
1%
#205000
b1101 3
b1101 B
b1001 9
b1001 A
b1001 /
1(
#210000
b1110111 )
b1110111 1
0(
0%
#215000
b1111 3
b1111 B
b1010 9
b1010 A
b1010 /
1(
#217000
b1000 2
b1000 D
b11111111111111111111111111111111 E
b1100 ;
b1100 C
b1111 :
1%
#220000
b10001111 )
b10001111 1
0(
#224000
0%
#225000
b1110 3
b1110 B
b1011 9
b1011 A
b1011 /
1(
#230000
b11001110 )
b11001110 1
0(
#231000
b1010 2
b1010 D
b11111111111111111111111111111111 E
b1111 ;
b1111 C
b1110 :
1%
#235000
b1010 3
b1010 B
b1100 9
b1100 A
b1100 /
1(
#238000
0%
#240000
b11000101 )
b11000101 1
0(
#245000
b1011 3
b1011 B
b1011 2
b1011 D
b11111111111111111111111111111111 E
b1101 9
b1101 A
b1110 ;
b1110 C
b1010 :
b1101 /
1(
1%
#250000
b10111101 )
b10111101 1
0(
#252000
0%
#255000
b1001 3
b1001 B
b1110 9
b1110 A
b1110 /
1(
#259000
b1100 2
b1100 D
b11111111111111111111111111111111 E
b1010 ;
b1010 C
b1001 :
1%
#260000
b1100101 )
b1100101 1
0(
#265000
b1000 3
b1000 B
b1111 9
b1111 A
b1111 /
1(
#266000
0%
#270000
b1010 )
b1010 1
0(
#273000
b1110 2
b1110 D
b11111111111111111111111111111111 E
b1001 ;
b1001 C
b1000 :
1%
#275000
1"
b11000 3
b11000 B
b10000 9
b10000 A
b10000 /
1(
#280000
b100000 )
b100000 1
0(
0%
#285000
1(
#287000
b1111 2
b1111 D
b11111111111111111111111111111111 E
b1000 ;
b1000 C
b11000 :
1%
#290000
b10011101 )
b10011101 1
0(
#294000
0%
#295000
1(
#300000
b10011 )
b10011 1
0(
#301000
b11111111111111111111111111111111 E
b10000 2
b10000 D
b11000 ;
b11000 C
1%
#305000
1(
#308000
0%
#310000
b1010011 )
b1010011 1
0(
#315000
1(
1%
#320000
b11010101 )
b11010101 1
0(
#322000
0%
#325000
1(
#329000
1%
#330000
b10101110 )
b10101110 1
0(
#335000
1(
#336000
0%
#340000
b11001111 )
b11001111 1
0(
#343000
1%
#345000
1(
#350000
b1010 )
b1010 1
0(
0%
#355000
1(
#357000
1%
#360000
0*
0(
#364000
0%
#365000
1(
#370000
0(
#371000
1%
#375000
1(
#378000
0%
#380000
0(
#385000
1(
1%
#390000
0(
#392000
0%
#395000
1(
#399000
1%
#400000
0(
#405000
1(
#406000
0%
#410000
0(
#413000
1%
#415000
1(
#420000
0(
0%
#425000
1(
#427000
1%
#430000
0(
#434000
0%
#435000
1(
#440000
0(
#441000
1%
#445000
1(
#448000
0%
#450000
0(
#455000
1(
1%
#460000
0(
#462000
1&
0%
#465000
1(
#469000
b1100011 !
b1100011 0
b1 5
b1 =
b1 6
b1 <
b1 -
b10000001 F
1%
#470000
0(
#475000
b1 7
1(
#476000
0%
#480000
0(
#483000
b10001101 !
b10001101 0
b11 5
b11 =
b10 6
b10 <
b10 -
b1100011 F
1%
#485000
0"
b1 4
b1 ?
b11111111111111111111111111111111 @
b1 8
b1 >
b11 7
1(
#490000
0(
0%
#495000
b10 4
b10 ?
b11111111111111111111111111111111 @
b11 8
b11 >
1(
#497000
b10010 !
b10010 0
b10 5
b10 =
b11 6
b11 <
b11 -
b10001101 F
1%
#500000
0(
#504000
0%
#505000
b10 7
1(
#510000
0(
#511000
b1101 !
b1101 0
b110 5
b110 =
b100 6
b100 <
b100 -
b10010 F
1%
#515000
b11 4
b11 ?
b11111111111111111111111111111111 @
b10 8
b10 >
b110 7
1(
#518000
0%
#520000
0(
#525000
b100 4
b100 ?
b11111111111111111111111111111111 @
b111101 !
b111101 0
b111 5
b111 =
b110 8
b110 >
b101 6
b101 <
b101 -
b1101 F
1(
1%
#530000
0(
#532000
0%
#535000
b111 7
1(
#539000
b10001100 !
b10001100 0
b101 5
b101 =
b110 6
b110 <
b110 -
b111101 F
1%
#540000
0(
#545000
b101 4
b101 ?
b11111111111111111111111111111111 @
b111 8
b111 >
b101 7
1(
#546000
0%
#550000
0(
#553000
b11000110 !
b11000110 0
b100 5
b100 =
b111 6
b111 <
b111 -
b10001100 F
1%
#555000
b110 4
b110 ?
b11111111111111111111111111111111 @
b101 8
b101 >
b100 7
1(
#560000
0(
0%
#565000
b111 4
b111 ?
b11111111111111111111111111111111 @
b100 8
b100 >
1(
#567000
b10101010 !
b10101010 0
b1100 5
b1100 =
b1000 6
b1000 <
b1000 -
b11000110 F
1%
#570000
0(
#574000
0%
#575000
b1100 7
1(
#580000
0(
#581000
b1110111 !
b1110111 0
b1101 5
b1101 =
b1001 6
b1001 <
b1001 -
b10101010 F
1%
#585000
b1000 4
b1000 ?
b11111111111111111111111111111111 @
b1100 8
b1100 >
b1101 7
1(
#588000
0%
#590000
0(
#595000
b1001 4
b1001 ?
b11111111111111111111111111111111 @
b10001111 !
b10001111 0
b1111 5
b1111 =
b1101 8
b1101 >
b1010 6
b1010 <
b1010 -
b1110111 F
1(
1%
#600000
0(
#602000
0%
#605000
b1111 7
1(
#609000
b11001110 !
b11001110 0
b1110 5
b1110 =
b1011 6
b1011 <
b1011 -
b10001111 F
1%
#610000
0(
#615000
b1010 4
b1010 ?
b11111111111111111111111111111111 @
b1111 8
b1111 >
b1110 7
1(
#616000
0%
#620000
0(
#623000
b11000101 !
b11000101 0
b1010 5
b1010 =
b1100 6
b1100 <
b1100 -
b11001110 F
1%
#625000
b1011 4
b1011 ?
b11111111111111111111111111111111 @
b1110 8
b1110 >
b1010 7
1(
#630000
0(
0%
#635000
b1100 4
b1100 ?
b11111111111111111111111111111111 @
b1010 8
b1010 >
1(
#637000
b10111101 !
b10111101 0
b1011 5
b1011 =
b1101 6
b1101 <
b1101 -
b11000101 F
1%
#640000
0(
#644000
0%
#645000
b1011 7
1(
#650000
0(
#651000
b1100101 !
b1100101 0
b1001 5
b1001 =
b1110 6
b1110 <
b1110 -
b10111101 F
1%
#655000
b1101 4
b1101 ?
b11111111111111111111111111111111 @
b1011 8
b1011 >
b1001 7
1(
#658000
0%
#660000
0(
#665000
b1110 4
b1110 ?
b11111111111111111111111111111111 @
b1010 !
b1010 0
b1000 5
b1000 =
b1001 8
b1001 >
b1111 6
b1111 <
b1111 -
b1100101 F
1(
1%
#670000
0(
#672000
0%
#675000
b1000 7
1(
#679000
1#
b10000001 !
b10000001 0
b11000 5
b11000 =
b10000 6
b10000 <
b10000 -
b1010 F
1%
#680000
0(
#685000
b1111 4
b1111 ?
b11111111111111111111111111111111 @
b1000 8
b1000 >
b11000 7
1(
#686000
0%
#690000
0(
#693000
1%
#695000
b11111111111111111111111111111111 @
b10000 4
b10000 ?
b11000 8
b11000 >
1(
