divide_by_3_clk/div_3.v
module div_3 (
    input clk,
    input areset,

    output div_3_clk
);

reg [1:0] pos_counter, neg_counter;

always @(posedge clk, posedge areset) begin
    if (areset) begin
        pos_counter <= 2'b00;
    end else begin
        if (pos_counter == 2'b10) begin
            pos_counter <= 2'b00;
        end else begin
            pos_counter <= pos_counter + 1;
        end
    end
end

always @(negedge clk, posedge areset) begin
    if (areset) begin
        neg_counter <= 2'b00;
    end else begin
        if (neg_counter == 2'b10) begin
            neg_counter <= 2'b00;
        end else begin
            neg_counter <= neg_counter + 1;
        end
    end
end

assign div_3_clk = (neg_counter == 2'b10) || (pos_counter == 2'b10);

endmodule

divide_by_3_clk/div_3_tb.v
`timescale 1ns/1ps

module div_3_tb;

    reg  clk;
    reg  areset;
    wire div_3_clk;

    // DUT
    div_3 dut (
        .clk       (clk),
        .areset    (areset),
        .div_3_clk (div_3_clk)
    );

    // 100 MHz reference clock (10 ns period)
    initial clk = 1'b0;
    always #5 clk = ~clk;

    // Stimulus
    initial begin
        $dumpfile("div_3_tb.vcd");
        $dumpvars(0, div_3_tb);

        areset = 1'b1;
        repeat (3) @(posedge clk);
        @(negedge clk) areset = 1'b0;

        // run long enough to see several output periods
        repeat (30) @(posedge clk);

        // exercise async reset again mid-stream
        areset = 1'b1;
        #7 areset = 1'b0;

        repeat (20) @(posedge clk);

        $display("Simulation finished at %0t", $time);
        $finish;
    end

    // Simple checker: measure output period once out of reset
    real t_rise, prev_rise, meas_period;
    initial begin
        prev_rise = 0.0;
        forever begin
            @(posedge div_3_clk);
            t_rise = $realtime;
            if (prev_rise != 0.0 && !areset) begin
                meas_period = t_rise - prev_rise;
                $display("[%0t] div_3_clk period = %0.1f ns (expect 30.0)", $time, meas_period);
            end
            prev_rise = t_rise;
        end
    end

endmodule

divide_by_3_clk/div_3_tb.vcd
$date
	Tue Sep  8 20:44:17 2026
$end
$version
	Icarus Verilog
$end
$timescale
	1ps
$end
$scope module div_3_tb $end
$var wire 1 ! div_3_clk $end
$var reg 1 " areset $end
$var reg 1 # clk $end
$var real 1 $ meas_period $end
$var real 1 % prev_rise $end
$var real 1 & t_rise $end
$scope module dut $end
$var wire 1 " areset $end
$var wire 1 # clk $end
$var wire 1 ! div_3_clk $end
$var reg 2 ' neg_counter [1:0] $end
$var reg 2 ( pos_counter [1:0] $end
$upscope $end
$upscope $end
$enddefinitions $end
$comment Show the parameter values. $end
$dumpall
$end
#0
$dumpvars
b0 (
b0 '
r0 &
r0 %
r0 $
0#
1"
0!
$end
#5000
1#
#10000
0#
#15000
1#
#20000
0#
#25000
1#
#30000
b1 '
0"
0#
#35000
b1 (
1#
#40000
r40 %
r40 &
1!
b10 '
0#
#45000
b10 (
1#
#50000
b0 '
0#
#55000
0!
b0 (
1#
#60000
b1 '
0#
#65000
b1 (
1#
#70000
r70 %
r30 $
r70 &
1!
b10 '
0#
#75000
b10 (
1#
#80000
b0 '
0#
#85000
0!
b0 (
1#
#90000
b1 '
0#
#95000
b1 (
1#
#100000
r100 %
r100 &
1!
b10 '
0#
#105000
b10 (
1#
#110000
b0 '
0#
#115000
0!
b0 (
1#
#120000
b1 '
0#
#125000
b1 (
1#
#130000
r130 %
r130 &
1!
b10 '
0#
#135000
b10 (
1#
#140000
b0 '
0#
#145000
0!
b0 (
1#
#150000
b1 '
0#
#155000
b1 (
1#
#160000
r160 %
r160 &
1!
b10 '
0#
#165000
b10 (
1#
#170000
b0 '
0#
#175000
0!
b0 (
1#
#180000
b1 '
0#
#185000
b1 (
1#
#190000
r190 %
r190 &
1!
b10 '
0#
#195000
b10 (
1#
#200000
b0 '
0#
#205000
0!
b0 (
1#
#210000
b1 '
0#
#215000
b1 (
1#
#220000
r220 %
r220 &
1!
b10 '
0#
#225000
b10 (
1#
#230000
b0 '
0#
#235000
0!
b0 (
1#
#240000
b1 '
0#
#245000
b1 (
1#
#250000
r250 %
r250 &
1!
b10 '
0#
#255000
b10 (
1#
#260000
b0 '
0#
#265000
0!
b0 (
1#
#270000
b1 '
0#
#275000
b1 (
1#
#280000
r280 %
r280 &
1!
b10 '
0#
#285000
b10 (
1#
#290000
b0 '
0#
#295000
0!
b0 (
1#
#300000
b1 '
0#
#305000
b1 (
1#
#310000
r310 %
r310 &
1!
b10 '
0#
#315000
b10 (
1#
#320000
b0 '
0#
#325000
0!
b0 (
1"
1#
#330000
0#
#332000
0"
#335000
b1 (
1#
#340000
b1 '
0#
#345000
r345 %
r35 $
r345 &
1!
b10 (
1#
#350000
b10 '
0#
#355000
b0 (
1#
#360000
0!
b0 '
0#
#365000
b1 (
1#
#370000
b1 '
0#
#375000
r375 %
r30 $
r375 &
1!
b10 (
1#
#380000
b10 '
0#
#385000
b0 (
1#
#390000
0!
b0 '
0#
#395000
b1 (
1#
#400000
b1 '
0#
#405000
r405 %
r405 &
1!
b10 (
1#
#410000
b10 '
0#
#415000
b0 (
1#
#420000
0!
b0 '
0#
#425000
b1 (
1#
#430000
b1 '
0#
#435000
r435 %
r435 &
1!
b10 (
1#
#440000
b10 '
0#
#445000
b0 (
1#
#450000
0!
b0 '
0#
#455000
b1 (
1#
#460000
b1 '
0#
#465000
r465 %
r465 &
1!
b10 (
1#
#470000
b10 '
0#
#475000
b0 (
1#
#480000
0!
b0 '
0#
#485000
b1 (
1#
#490000
b1 '
0#
#495000
r495 %
r495 &
1!
b10 (
1#
#500000
b10 '
0#
#505000
b0 (
1#
#510000
0!
b0 '
0#
#515000
b1 (
1#
#520000
b1 '
0#
#525000
1!
b10 (
1#
